Day6/Serial_in_serial_out_RTL_design/siso.sv
module siso(
  input logic clk,
  input logic rst,
  input logic si,
  output logic so
);
  
  logic [3:0] temp;
  
  always@(posedge clk) begin
    if(rst) begin
      temp <= 4'b0000;
      so <= 1'b0;
    end else begin
      temp <= temp << 1;
      temp[0] <= si;
      so <= temp[3];
    end
  end
    
endmodule

Day6/Serial_in_serial_out_RTL_design/siso_tb.sv
module siso_tb;
  logic clk;
  logic rst;
  logic si;
  logic so;
  
  logic so_e;
  
  logic[3:0] temp;
  
  siso siso_inst(.*);
  
  function void compare(input logic clk, input logic rst, input logic si, input logic so, input logic so_e);
    if(rst) begin
      so_e = 0;
      temp = 0;
    end else begin
      so_e = temp[3];
      temp = temp << 1;
      temp[0] = si;
    end
    
    if(so_e == so) begin
      $display("Pass : so is %0h ", so);
    end else begin
      $display("Fail : so is %0h  and so_e is %0h ", so, so_e);
    end   
  endfunction
  
  always@(*) begin
    #1 clk <= ~clk;
  end
    
  initial begin
    clk=0;rst=1;
    @(posedge clk);
    @(posedge clk);
    compare(clk, rst, si, so, so_e);
    rst=0;
      repeat(20) begin
        si = $random();
        @(posedge clk);
        compare(clk, rst, si, so, so_e);
      end
    $finish();
  end
  
  initial begin
    $dumpfile("dump.vcd");
    $dumpvars;
  end
  
endmodule

Day6/Serial_in_serial_out_RTL_design/dump.vcd
$date
	Sun Mar  5 02:32:25 2023
$end

$version
	Synopsys VCS version S-2021.09
$end

$timescale
	1ns
$end

$comment Csum: 1 2948521254efda4b $end


$scope module siso_tb $end
$var reg 1 ! clk $end
$var reg 1 " rst $end
$var reg 1 # si $end
$var reg 1 $ so $end
$var reg 1 % so_e $end
$var reg 4 & temp [3:0] $end

$scope function compare $end
$var reg 1 ' clk $end
$var reg 1 ( rst $end
$var reg 1 ) si $end
$var reg 1 * so $end
$var reg 1 + so_e $end
$upscope $end


$scope module siso_inst $end
$var reg 1 ! clk $end
$var reg 1 " rst $end
$var reg 1 # si $end
$var reg 1 $ so $end
$var reg 4 , temp [3:0] $end
$upscope $end

$upscope $end

$enddefinitions $end

#0
$dumpvars
0!
x'
x(
x)
x*
x+
1"
x#
x$
bxxxx ,
bxxxx &
x%
$end
#1
1!
b0000 ,
0$
#2
0!
#3
1!
1'
1(
0*
0+
b0000 &
0"
0#
#4
0!
#5
1!
0(
0)
1#
b0001 ,
#6
0!
#7
1!
1)
b0001 &
b0011 ,
#8
0!
#9
1!
b0011 &
b0111 ,
#10
0!
#11
1!
b0111 &
b1111 ,
#12
0!
#13
1!
b1111 &
1$
#14
0!
#15
1!
1*
1+
#16
0!
#17
1!
0#
b1110 ,
#18
0!
#19
1!
0)
b1110 &
1#
b1101 ,
#20
0!
#21
1!
1)
b1101 &
b1011 ,
#22
0!
#23
1!
b1011 &
0#
b0110 ,
#24
0!
#25
1!
0)
b0110 &
1#
b1101 ,
0$
#26
0!
#27
1!
1)
0*
0+
b1101 &
b1011 ,
1$
#28
0!
#29
1!
1*
1+
b1011 &
0#
b0110 ,
#30
0!
#31
1!
0)
b0110 &
1#
b1101 ,
0$
#32
0!
#33
1!
1)
0*
0+
b1101 &
0#
b1010 ,
1$
#34
0!
#35
1!
0)
1*
1+
b1010 &
1#
b0101 ,
#36
0!
#37
1!
1)
b0101 &
0#
b1010 ,
0$
#38
0!
#39
1!
0)
0*
0+
b1010 &
1#
b0101 ,
1$
#40
0!
#41
1!
1)
1*
1+
b0101 &
b1011 ,
0$
#42
0!
#43
1!
0*
0+
b1011 &
