Day_11/JK_Flip_flop/jk_ff.sv
module jk_ff(
  input logic j,
  input logic k,
  input logic clk,
  output logic q,
  output logic qbar
);
  always@(posedge clk) begin
    case({j,k}) 
      2'b00 : q <= q;
      2'b01 : q <= 0;
      2'b10 : q <= 1;
      2'b11 : q <= ~q;
      default : q <= q;
    endcase    
  end
  
  assign qbar = ~q; 
  
endmodule

Day_11/JK_Flip_flop/jk_ff_tb.sv
module jk_ff_tb;
  logic j;
  logic k;
  logic clk;
  logic q;
  logic qbar;
   
  logic q_e;

  jk_ff jk_ff_inst(.*);
  
  always@(*) begin
    #1 clk <= ~clk;
  end
  
  function void compare(input logic q, input logic q_e);
    if(q === q_e) begin
      $display("Pass");
    end else begin
      $display(" Time is %0t , j is %0h and k is %0h ,Fail q is %0h and q_e is %0h",$time,j,k, q, q_e);
    end
  endfunction
  

  function void model(input logic j, input logic k, input logic q, output logic q_e);
    
    q_e = (j && k) ? ~q : j ? 1 : k ? 0 : q_e;
    
  endfunction 
                            
  initial begin
    clk=0;j=0;k=1;
    @(negedge clk);
    model(j,k,q,q_e);
    @(negedge clk);
    compare(q,q_e);
    k=0;
    repeat(20) begin
      j = $random();
      k = $random();
      model(j,k,q,q_e);
      @(posedge clk);
      compare(q,q_e);
    end
    $finish();
  end
               
  initial begin
    $dumpfile("dump.vcd");
    $dumpvars;
  end
  
endmodule

Day_11/JK_Flip_flop/dump.vcd
$date
	Sun Mar 19 04:08:22 2023
$end

$version
	Synopsys VCS version S-2021.09
$end

$timescale
	1ns
$end

$comment Csum: 1 69087bcaf80fadda $end


$scope module jk_ff_tb $end
$var reg 1 ! j $end
$var reg 1 " k $end
$var reg 1 # clk $end
$var reg 1 $ q $end
$var reg 1 % qbar $end
$var reg 1 & q_e $end

$scope function compare $end
$var reg 1 ' q $end
$var reg 1 ( q_e $end
$upscope $end


$scope function model $end
$var reg 1 ) j $end
$var reg 1 * k $end
$var reg 1 + q $end
$var reg 1 , q_e $end
$upscope $end


$scope module jk_ff_inst $end
$var reg 1 ! j $end
$var reg 1 " k $end
$var reg 1 # clk $end
$var reg 1 $ q $end
$var reg 1 % qbar $end
$upscope $end

$upscope $end

$enddefinitions $end

#0
$dumpvars
0#
x'
x(
0!
1"
x)
x*
x+
x,
x$
x&
x%
$end
#1
1#
0$
1%
#2
0#
0)
1*
0+
0,
0&
#3
1#
#4
0#
0'
0(
0"
1"
#5
1#
1!
1)
1,
1&
1$
0%
#6
0#
#7
1#
1'
1(
1+
0,
0&
0$
1%
#8
0#
#9
1#
0'
0(
0*
0+
1,
0"
1&
1$
0%
#10
0#
#11
1#
1'
1(
1*
1+
0,
1"
0&
0$
1%
#12
0#
#13
1#
0'
0(
0!
0)
0+
#14
0#
#15
1#
1!
1)
0*
1,
0"
1&
1$
0%
#16
0#
#17
1#
1'
1(
1+
#18
0#
#19
1#
#20
0#
#21
1#
1*
0,
1"
0&
0$
1%
#22
0#
#23
1#
0'
0(
0!
0)
0+
#24
0#
#25
1#
0*
0"
#26
0#
#27
1#
1*
1"
#28
0#
#29
1#
#30
0#
#31
1#
1!
1)
1,
1&
1$
0%
#32
0#
#33
1#
1'
1(
0*
1+
0"
#34
0#
#35
1#
0!
0)
#36
0#
#37
1#
1*
0,
1"
0&
0$
1%
#38
0#
#39
1#
0'
0(
0+
#40
0#
#41
1#
1!
1)
1,
1&
1$
0%
#42
0#
#43
1#
1'
1(
