Day7/Serial_in_parallel_out_RTL_deign/sipo.sv
module sipo(
  input logic clk,
  input logic rst,
  input logic si,
  output logic [3:0] po
);
  
  always@(posedge clk) begin
    if(rst) begin
      po <= 4'b0;
    end else begin
      po <= po << 1;
      po[0] <= si;
    end
  end
    
endmodule

Day7/Serial_in_parallel_out_RTL_deign/sipo_tb.sv
module sipo_tb;
  logic clk;
  logic rst;
  logic si;
  logic [3:0] po;
  
  logic [3:0] po_e;
  
  sipo sipo_inst(.*);
  
  function void compare(input logic clk, input logic rst, input logic si, input logic [3:0] po, input logic [3:0] po_e); 
    if(po_e == po) begin
      $monitor("Pass : po is %0h ", po);
    end else begin
      $monitor("Fail : po is %0h  and po_e is %0h ", po, po_e);
    end   
  endfunction
  
  function void model(input logic clk, input logic rst, input logic si, input logic [3:0] po, output logic [3:0] po_e);
    if(rst) begin
      po_e = 'h0;
    end else begin
      po_e = po_e << 1;
      po_e[0] = si;
    end
  endfunction
  
  always@(*) begin
    #1 clk <= ~clk;
  end
    
  initial begin
    clk=0;rst=1;
    model(clk, rst, si, po, po_e);
    @(posedge clk);
    model(clk, rst, si, po, po_e);
    @(posedge clk);
    compare(clk, rst, si, po, po_e);
    rst=0;
      repeat(20) begin
        si = $random();
        model(clk, rst, si, po, po_e);
        @(posedge clk);
        compare(clk, rst, si, po, po_e);
      end
    $finish();
  end
  
  initial begin
    $dumpfile("dump.vcd");
    $dumpvars;
  end
endmodule

Day7/Serial_in_parallel_out_RTL_deign/dump.vcd
$date
	Sun Mar  5 03:56:57 2023
$end

$version
	Synopsys VCS version S-2021.09
$end

$timescale
	1ns
$end

$comment Csum: 1 3e4edd60f1a2697a $end


$scope module sipo_tb $end
$var reg 1 ! clk $end
$var reg 1 " rst $end
$var reg 1 # si $end
$var reg 4 $ po [3:0] $end
$var reg 4 % po_e [3:0] $end

$scope function compare $end
$var reg 1 & clk $end
$var reg 1 ' rst $end
$var reg 1 ( si $end
$var reg 4 ) po [3:0] $end
$var reg 4 * po_e [3:0] $end
$upscope $end


$scope function model $end
$var reg 1 + clk $end
$var reg 1 , rst $end
$var reg 1 - si $end
$var reg 4 . po [3:0] $end
$var reg 4 / po_e [3:0] $end
$upscope $end


$scope module sipo_inst $end
$var reg 1 ! clk $end
$var reg 1 " rst $end
$var reg 1 # si $end
$var reg 4 $ po [3:0] $end
$upscope $end

$upscope $end

$enddefinitions $end

#0
$dumpvars
0!
x&
x'
x(
0+
1,
x-
1"
x#
bxxxx )
bxxxx *
bxxxx .
b0000 /
bxxxx $
b0000 %
$end
#1
1!
1+
b0000 $
#2
0!
#3
1!
1&
1'
b0000 )
b0000 *
0"
0#
0,
0-
b0000 .
#4
0!
#5
1!
0'
0(
1#
1-
b0001 /
b0001 %
b0001 $
#6
0!
#7
1!
1(
b0001 )
b0001 *
b0001 .
b0011 /
b0011 %
b0011 $
#8
0!
#9
1!
b0011 )
b0011 *
b0011 .
b0111 /
b0111 %
b0111 $
#10
0!
#11
1!
b0111 )
b0111 *
b0111 .
b1111 /
b1111 %
b1111 $
#12
0!
#13
1!
b1111 )
b1111 *
b1111 .
#14
0!
#15
1!
#16
0!
#17
1!
0#
0-
b1110 /
b1110 %
b1110 $
#18
0!
#19
1!
0(
b1110 )
b1110 *
1#
1-
b1110 .
b1101 /
b1101 %
b1101 $
#20
0!
#21
1!
1(
b1101 )
b1101 *
b1101 .
b1011 /
b1011 %
b1011 $
#22
0!
#23
1!
b1011 )
b1011 *
0#
0-
b1011 .
b0110 /
b0110 %
b0110 $
#24
0!
#25
1!
0(
b0110 )
b0110 *
1#
1-
b0110 .
b1101 /
b1101 %
b1101 $
#26
0!
#27
1!
1(
b1101 )
b1101 *
b1101 .
b1011 /
b1011 %
b1011 $
#28
0!
#29
1!
b1011 )
b1011 *
0#
0-
b1011 .
b0110 /
b0110 %
b0110 $
#30
0!
#31
1!
0(
b0110 )
b0110 *
1#
1-
b0110 .
b1101 /
b1101 %
b1101 $
#32
0!
#33
1!
1(
b1101 )
b1101 *
0#
0-
b1101 .
b1010 /
b1010 %
b1010 $
#34
0!
#35
1!
0(
b1010 )
b1010 *
1#
1-
b1010 .
b0101 /
b0101 %
b0101 $
#36
0!
#37
1!
1(
b0101 )
b0101 *
0#
0-
b0101 .
b1010 /
b1010 %
b1010 $
#38
0!
#39
1!
0(
b1010 )
b1010 *
1#
1-
b1010 .
b0101 /
b0101 %
b0101 $
#40
0!
#41
1!
1(
b0101 )
b0101 *
b0101 .
b1011 /
b1011 %
b1011 $
#42
0!
#43
1!
b1011 )
b1011 *
