Day4/single_port_ram_RTL_design/single_port_ram.sv
module single_port_ram #(
  parameter DATA_WIDTH = 8,
  parameter ADDR_WIDTH = 6
)(
  input logic clk,
  input logic rst,
  input logic [DATA_WIDTH-1 : 0] data,
  input logic [ADDR_WIDTH-1 : 0] addr,
  input logic enable,
  output logic [DATA_WIDTH-1 : 0] q
);
  logic [DATA_WIDTH-1 : 0] ram[0 : 2**(ADDR_WIDTH)-1];
  
  always@(posedge clk) begin
    if(rst) begin
      q <= 0;
    end else begin
      if (enable) begin
        ram[addr] <= data;
      end else begin
        q <= ram[addr];
      end 
    end 
  end
endmodule

Day4/single_port_ram_RTL_design/single_port_ram_tb.sv
module single_port_ram_tb;
  parameter DATA_WIDTH = 8;
  parameter ADDR_WIDTH = 6;
  logic clk;
  logic rst;
  logic [DATA_WIDTH-1 : 0] data;
  logic [ADDR_WIDTH-1 : 0] addr;
  logic enable;
  logic [DATA_WIDTH-1 : 0] q;
  
  logic [DATA_WIDTH-1 : 0] q_e;
  logic [DATA_WIDTH-1 : 0] q1[$];
  
  
  single_port_ram #(.DATA_WIDTH(DATA_WIDTH), .ADDR_WIDTH(ADDR_WIDTH)) single_port_ram_inst (.*);
  
  function void compare(input logic clk, input logic rst, input logic [DATA_WIDTH-1 : 0] data, input logic [ADDR_WIDTH-1 : 0] addr, input logic enable, input logic [DATA_WIDTH-1 : 0] q, input logic [DATA_WIDTH-1 : 0] q_e);
    
    logic [DATA_WIDTH-1 : 0] ram[0 : 2**(ADDR_WIDTH)-1];
    
    if(rst) begin
      q_e = 0;
    end else begin
      if (enable) begin
        ram[addr] = data;
      end else begin
        q_e = ram[addr];
      end 
    end 
      
    if (enable == 0) begin
      if(q == q_e) begin
        $display("Pass %0t: q is %0h", $time, q);
      end else begin
        $display("Fail %0t : q is %0h and q_e is %0h ", $time, q, q_e);
      end
    end  
      
  endfunction
      
  always@(*) begin
    #1 clk <= ~clk;
  end
  
  initial begin  
    clk = 0;rst = 1;
    @(posedge clk);
    @(posedge clk);
    compare(clk,rst, data, addr, enable, q, q_e);
    rst = 0;
    data = $random();
    addr = $random();
    enable = 1'b1;   
    q1.push_back(addr); 
    @(posedge clk);
    compare(clk,rst, data, addr, enable, q, q_e);
    repeat(20) begin
      data = $random();
      q1.shuffle();
      enable = $random();
      if(enable == 0) begin
        addr = q1[0];
      end else begin
        addr = $random();
      end
         
      if(enable) begin
        q1.push_back(addr); 
      end
      @(posedge clk);
      compare(clk,rst, data, addr, enable, q, q_e);
    end
    $finish();
  end
  
  initial begin
    $dumpfile("dump.vcd");
    $dumpvars;
  end  
endmodule

Day4/single_port_ram_RTL_design/dump.vcd
$date
	Sat Mar  4 13:24:53 2023
$end

$version
	Synopsys VCS version S-2021.09
$end

$timescale
	1ns
$end

$comment Csum: 1 61d2aa90f4cfbaa9 $end


$scope module single_port_ram_tb $end
$var reg 1 ! clk $end
$var reg 1 " rst $end
$var reg 8 # data [7:0] $end
$var reg 6 $ addr [5:0] $end
$var reg 1 % enable $end
$var reg 8 & q [7:0] $end
$var reg 8 ' q_e [7:0] $end

$scope begin unnamed$$_vcs_2 $end
$upscope $end


$scope begin unnamed$$_vcs_0 $end
$upscope $end


$scope begin unnamed$$_vcs_1 $end
$upscope $end


$scope module single_port_ram_inst $end
$var reg 1 ! clk $end
$var reg 1 " rst $end
$var reg 8 # data [7:0] $end
$var reg 6 $ addr [5:0] $end
$var reg 1 % enable $end
$var reg 8 & q [7:0] $end
$upscope $end

$upscope $end

$enddefinitions $end

#0
$dumpvars
0!
x%
1"
bxxxxxx $
bxxxxxxxx #
bxxxxxxxx &
bxxxxxxxx '
$end
#1
1!
b00000000 &
#2
0!
#3
1!
0"
b00100100 #
b000001 $
1%
#4
0!
#5
1!
b00001001 #
b001101 $
#6
0!
#7
1!
b10001101 #
b010010 $
#8
0!
#9
1!
b00000001 #
b110110 $
#10
0!
#11
1!
b00111101 #
b001100 $
#12
0!
#13
1!
b11111001 #
0%
b000001 $
b00100100 &
#14
0!
#15
1!
b11000101 #
#16
0!
#17
1!
b11100101 #
1%
b010010 $
#18
0!
#19
1!
b10001111 #
0%
b001101 $
b00001001 &
#20
0!
#21
1!
b11001110 #
b001100 $
b00111101 &
#22
0!
#23
1!
b11000101 #
b010010 $
b11100101 &
#24
0!
#25
1!
b10111101 #
1%
b100101 $
#26
0!
#27
1!
b01100011 #
0%
b000001 $
b00100100 &
#28
0!
#29
1!
b10000000 #
b001100 $
b00111101 &
#30
0!
#31
1!
b10101010 #
1%
b010110 $
#32
0!
#33
1!
b00010011 #
b010011 $
#34
0!
#35
1!
b01101011 #
b000010 $
#36
0!
#37
1!
b10101110 #
b001111 $
#38
0!
#39
1!
b00100011 #
0%
b010110 $
b10101010 &
#40
0!
#41
1!
b11001010 #
b010010 $
b11100101 &
#42
0!
#43
1!
b11110010 #
b100101 $
b10111101 &
