Day3/counter_rtl_design/counter.sv
module counter(
  input logic clk,
  input logic rst,
  output logic [3:0] count
);
  
  always@(posedge clk) begin  
    if(rst) begin
      count <= 4'b0000;
    end else begin
      count <= count + 1;
    end
  end
  
endmodule

Day3/counter_rtl_design/counter_tb.sv
module counter_tb;
  logic clk;
  logic rst;
  logic [3:0] count;
  
  logic [3:0] count_e;       
  
  counter counter_inst(.*);
  
  always@(clk) begin
    #1 clk <= ~clk;
  end 
  
  function void compare(input logic [3:0]count, input logic [3:0]count_e);
    if(count == count_e) begin
      $display("Pass : count is %0h", count);
    end else begin
      $display("Fail : count is %0h count_e is %0h", count, count_e);
    end 
  endfunction
    
  initial begin
    clk=0;rst=1; count_e = 0;
    @(posedge clk);
    @(posedge clk);
    rst=0;
    repeat(3) begin
      repeat(20) begin
        count_e <= count_e + 1;
        compare(count,count_e);
        @(posedge clk);
      end 
      rst=1; count_e = 0;
      @(posedge clk);
      rst=0;
    end
    $finish();
  end
  
  initial begin
    $dumpfile("dump.vcd");
    $dumpvars;
  end
  
endmodule

Day3/counter_rtl_design/dump.vcd
$date
	Sun Feb 26 02:40:41 2023
$end

$version
	Synopsys VCS version S-2021.09
$end

$timescale
	1ns
$end

$comment Csum: 1 3f7d208d0a7846df $end


$scope module counter_tb $end
$var reg 1 ! clk $end
$var reg 1 " rst $end
$var reg 4 # count [3:0] $end
$var reg 4 $ count_e [3:0] $end

$scope function compare $end
$var reg 4 % count [3:0] $end
$var reg 4 & count_e [3:0] $end
$upscope $end


$scope module counter_inst $end
$var reg 1 ! clk $end
$var reg 1 " rst $end
$var reg 4 # count [3:0] $end
$upscope $end

$upscope $end

$enddefinitions $end

#0
$dumpvars
0!
1"
bxxxx %
bxxxx &
bxxxx #
b0000 $
$end
#1
1!
b0000 #
#2
0!
#3
1!
0"
b0000 %
b0000 &
b0001 $
b0001 #
#4
0!
#5
1!
b0001 %
b0001 &
b0010 $
b0010 #
#6
0!
#7
1!
b0010 %
b0010 &
b0011 $
b0011 #
#8
0!
#9
1!
b0011 %
b0011 &
b0100 $
b0100 #
#10
0!
#11
1!
b0100 %
b0100 &
b0101 $
b0101 #
#12
0!
#13
1!
b0101 %
b0101 &
b0110 $
b0110 #
#14
0!
#15
1!
b0110 %
b0110 &
b0111 $
b0111 #
#16
0!
#17
1!
b0111 %
b0111 &
b1000 $
b1000 #
#18
0!
#19
1!
b1000 %
b1000 &
b1001 $
b1001 #
#20
0!
#21
1!
b1001 %
b1001 &
b1010 $
b1010 #
#22
0!
#23
1!
b1010 %
b1010 &
b1011 $
b1011 #
#24
0!
#25
1!
b1011 %
b1011 &
b1100 $
b1100 #
#26
0!
#27
1!
b1100 %
b1100 &
b1101 $
b1101 #
#28
0!
#29
1!
b1101 %
b1101 &
b1110 $
b1110 #
#30
0!
#31
1!
b1110 %
b1110 &
b1111 $
b1111 #
#32
0!
#33
1!
b1111 %
b1111 &
b0000 $
b0000 #
#34
0!
#35
1!
b0000 %
b0000 &
b0001 $
b0001 #
#36
0!
#37
1!
b0001 %
b0001 &
b0010 $
b0010 #
#38
0!
#39
1!
b0010 %
b0010 &
b0011 $
b0011 #
#40
0!
#41
1!
b0011 %
b0011 &
b0100 $
b0100 #
#42
0!
#43
1!
1"
b0000 $
b0000 #
#44
0!
#45
1!
0"
b0000 %
b0000 &
b0001 $
b0001 #
#46
0!
#47
1!
b0001 %
b0001 &
b0010 $
b0010 #
#48
0!
#49
1!
b0010 %
b0010 &
b0011 $
b0011 #
#50
0!
#51
1!
b0011 %
b0011 &
b0100 $
b0100 #
#52
0!
#53
1!
b0100 %
b0100 &
b0101 $
b0101 #
#54
0!
#55
1!
b0101 %
b0101 &
b0110 $
b0110 #
#56
0!
#57
1!
b0110 %
b0110 &
b0111 $
b0111 #
#58
0!
#59
1!
b0111 %
b0111 &
b1000 $
b1000 #
#60
0!
#61
1!
b1000 %
b1000 &
b1001 $
b1001 #
#62
0!
#63
1!
b1001 %
b1001 &
b1010 $
b1010 #
#64
0!
#65
1!
b1010 %
b1010 &
b1011 $
b1011 #
#66
0!
#67
1!
b1011 %
b1011 &
b1100 $
b1100 #
#68
0!
#69
1!
b1100 %
b1100 &
b1101 $
b1101 #
#70
0!
#71
1!
b1101 %
b1101 &
b1110 $
b1110 #
#72
0!
#73
1!
b1110 %
b1110 &
b1111 $
b1111 #
#74
0!
#75
1!
b1111 %
b1111 &
b0000 $
b0000 #
#76
0!
#77
1!
b0000 %
b0000 &
b0001 $
b0001 #
#78
0!
#79
1!
b0001 %
b0001 &
b0010 $
b0010 #
#80
0!
#81
1!
b0010 %
b0010 &
b0011 $
b0011 #
#82
0!
#83
1!
b0011 %
b0011 &
b0100 $
b0100 #
#84
0!
#85
1!
1"
b0000 $
b0000 #
#86
0!
#87
1!
0"
b0000 %
b0000 &
b0001 $
b0001 #
#88
0!
#89
1!
b0001 %
b0001 &
b0010 $
b0010 #
#90
0!
#91
1!
b0010 %
b0010 &
b0011 $
b0011 #
#92
0!
#93
1!
b0011 %
b0011 &
b0100 $
b0100 #
#94
0!
#95
1!
b0100 %
b0100 &
b0101 $
b0101 #
#96
0!
#97
1!
b0101 %
b0101 &
b0110 $
b0110 #
#98
0!
#99
1!
b0110 %
b0110 &
b0111 $
b0111 #
#100
0!
#101
1!
b0111 %
b0111 &
b1000 $
b1000 #
#102
0!
#103
1!
b1000 %
b1000 &
b1001 $
b1001 #
#104
0!
#105
1!
b1001 %
b1001 &
b1010 $
b1010 #
#106
0!
#107
1!
b1010 %
b1010 &
b1011 $
b1011 #
#108
0!
#109
1!
b1011 %
b1011 &
b1100 $
b1100 #
#110
0!
#111
1!
b1100 %
b1100 &
b1101 $
b1101 #
#112
0!
#113
1!
b1101 %
b1101 &
b1110 $
b1110 #
#114
0!
#115
1!
b1110 %
b1110 &
b1111 $
b1111 #
#116
0!
#117
1!
b1111 %
b1111 &
b0000 $
b0000 #
#118
0!
#119
1!
b0000 %
b0000 &
b0001 $
b0001 #
#120
0!
#121
1!
b0001 %
b0001 &
b0010 $
b0010 #
#122
0!
#123
1!
b0010 %
b0010 &
b0011 $
b0011 #
#124
0!
#125
1!
b0011 %
b0011 &
b0100 $
b0100 #
#126
0!
#127
1!
1"
b0000 $
b0000 #
#128
0!
#129
1!
0"
