Day_10/SR_flipflop/sr_ff.sv
module sr_ff(
  input logic s,
  input logic r,
  input logic clk,
  output logic q,
  output logic qbar
);
  always@(posedge clk) begin
    case({s,r})
      2'b00 : q <= q;
      2'b01 : q <= 0;
      2'b10 : q <= 1;
      2'b11 : q <= 1'bz;
      default : q <= 1'bz;
    endcase   
  end
  
  assign qbar = (q === 1'hz)? 1'hz: ~q;   
  
endmodule

Day_10/SR_flipflop/sr_ff_tb.sv
module sr_ff_tb;
  logic s;
  logic r;
  logic clk;
  logic q;
  logic qbar;
  
  logic q_e;

  sr_ff sr_ff_inst(.*);
  
  always@(*) begin
    #1 clk <= ~clk;
  end
  
  function void compare(input logic q, input logic q_e);
    if(q === q_e) begin
      $display(" Time is %0t, Pass ", $time);
    end else begin
      $display("Time is %0t, Fail  q is %0h and q_e is %0h s is %0h and r is %0h ", $time, q, q_e,s, r);
    end
    
  endfunction
  
  function void model(input logic s, input logic r, input logic clk, output logic q_e);
    
    q_e = (s && r) ? 'hz : s ? 1 : r ? 0 : q_e;
    
  endfunction
  
  initial begin
    clk=0;s=0;r=1;
    @(negedge clk);
    model(s, r, clk,q_e);
    @(negedge clk);
    compare(q, q_e);
    r=0;
    repeat(20) begin
      s = $random();
      r = $random();
      model(s, r, clk, q_e);
      @(posedge clk);
      compare(q, q_e);
    end
    $finish();
  end
  
  initial begin
    $dumpfile("dump.vcd");
    $dumpvars;
  end
  
endmodule

Day10/SR_flipflop/dump.vcd
$date
	Sat Mar 18 14:41:48 2023
$end

$version
	Synopsys VCS version S-2021.09
$end

$timescale
	1ns
$end

$comment Csum: 1 1c2d7f4cd701e924 $end


$scope module sr_ff_tb $end
$var reg 1 ! s $end
$var reg 1 " r $end
$var reg 1 # clk $end
$var reg 1 $ q $end
$var reg 1 % qbar $end
$var reg 1 & q_e $end

$scope function compare $end
$var reg 1 ' q $end
$var reg 1 ( q_e $end
$upscope $end


$scope function model $end
$var reg 1 ) s $end
$var reg 1 * r $end
$var reg 1 + clk $end
$var reg 1 , q_e $end
$upscope $end


$scope module sr_ff_inst $end
$var reg 1 ! s $end
$var reg 1 " r $end
$var reg 1 # clk $end
$var reg 1 $ q $end
$var reg 1 % qbar $end
$upscope $end

$upscope $end

$enddefinitions $end

#0
$dumpvars
0#
x'
x(
x+
x,
x*
x)
x$
x&
1"
0!
x%
$end
#1
1#
0$
1%
#2
0#
0)
1*
0+
0,
0&
#3
1#
#4
0#
0'
0(
0"
1"
#5
1#
1!
1)
1+
z,
z&
z$
x%
#6
0#
#7
1#
z'
z(
#8
0#
#9
1#
0*
1,
0"
1&
1$
0%
#10
0#
#11
1#
1'
1(
1*
z,
1"
z&
z$
x%
#12
0#
#13
1#
z'
z(
0!
0)
0,
0&
0$
1%
#14
0#
#15
1#
0'
0(
1!
1)
0*
1,
0"
1&
1$
0%
#16
0#
#17
1#
1'
1(
#18
0#
#19
1#
#20
0#
#21
1#
1*
z,
1"
z&
z$
x%
#22
0#
#23
1#
z'
z(
0!
0)
0,
0&
0$
1%
#24
0#
#25
1#
0'
0(
0*
0"
#26
0#
#27
1#
1*
1"
#28
0#
#29
1#
#30
0#
#31
1#
1!
1)
z,
z&
z$
x%
#32
0#
#33
1#
z'
z(
0*
1,
0"
1&
1$
0%
#34
0#
#35
1#
1'
1(
0!
0)
#36
0#
#37
1#
1*
0,
1"
0&
0$
1%
#38
0#
#39
1#
0'
0(
#40
0#
#41
1#
1!
1)
z,
z&
z$
x%
#42
0#
#43
1#
z'
z(
