Day9/D_flip_flop/d_ff.sv
module d_ff(
  input logic clk,
  input logic rst,
  input logic d,
  output logic q,
  output logic qbar
);
  
  logic q1;
  
  always@(posedge clk) begin
    if(rst) begin
      q <= 0;
    end else begin
      q1 <= d;
      q <= q1;
    end
    
  end
  
  
  assign qbar = ~q;
  
endmodule

Day9/D_flip_flop/d_ff_tb.sv
module d_ff_tb;
  logic clk;
  logic rst;
  logic d;
  logic q;
  logic qbar;
  
  d_ff d_ff_inst(.*);
  
  initial begin
    clk = 0; rst = 1;
    @(negedge clk);
    @(negedge clk);
    rst = 0;
    if(q == 0) begin
      $display("Pass ");
    end else begin
      $display("Fail");
    end
    repeat(20) begin
      d = $random();
      @(negedge clk);
      if(q == d) begin
        $display("Pass ");
      end else begin
        $display("Fail ");
      end
    end
    $finish();
  end
  
  always@(*) begin
   #1 clk <= ~clk;
  end
  
  initial begin
    $dumpfile("dump.vcd");
    $dumpvars;
  end
  
endmodule

Day9/D_flip_flop/dump.vcd
$date
	Sun Mar 12 01:54:33 2023
$end

$version
	Synopsys VCS version S-2021.09
$end

$timescale
	1ns
$end

$comment Csum: 1 7da29092d8e9faee $end


$scope module d_ff_tb $end
$var reg 1 ! clk $end
$var reg 1 " rst $end
$var reg 1 # d $end
$var reg 1 $ q $end
$var reg 1 % qbar $end

$scope module d_ff_inst $end
$var reg 1 ! clk $end
$var reg 1 " rst $end
$var reg 1 # d $end
$var reg 1 $ q $end
$var reg 1 % qbar $end
$var reg 1 & q1 $end
$upscope $end

$upscope $end

$enddefinitions $end

#0
$dumpvars
0!
x#
x$
x&
1"
x%
$end
#1
1!
0$
1%
#2
0!
#3
1!
#4
0!
0"
0#
#5
1!
0&
x$
x%
#6
0!
1#
#7
1!
1&
0$
1%
#8
0!
#9
1!
1$
0%
#10
0!
#11
1!
#12
0!
#13
1!
#14
0!
#15
1!
#16
0!
#17
1!
#18
0!
0#
#19
1!
0&
#20
0!
1#
#21
1!
1&
0$
1%
#22
0!
#23
1!
1$
0%
#24
0!
0#
#25
1!
0&
#26
0!
1#
#27
1!
1&
0$
1%
#28
0!
#29
1!
1$
0%
#30
0!
0#
#31
1!
0&
#32
0!
1#
#33
1!
1&
0$
1%
#34
0!
0#
#35
1!
0&
1$
0%
#36
0!
1#
#37
1!
1&
0$
1%
#38
0!
0#
#39
1!
0&
1$
0%
#40
0!
1#
#41
1!
1&
0$
1%
#42
0!
#43
1!
1$
0%
