Day8/Parallel_in_serial_out_RTL_design/piso.sv
module piso(
  input logic clk,
  input logic rst,
  input logic [3:0] pi,
  input logic load,
  output logic so
);
  logic [3:0] temp;
  
  always@(posedge clk) begin
    if(rst) begin
      so <= 1'b0;
      temp <= 4'b0000;
    end else begin
      if(load) begin
        temp <= pi;
      end else begin
        temp <= temp<<1;
      end 
    end
  end
    
  always@(*) begin
    so = temp[3];
  end
  
endmodule

Day8/Parallel_in_serial_out_RTL_design/piso_tb.sv
module piso_tb;
  logic clk;
  logic rst;
  logic [3:0] pi;
  logic load;
  logic so;
  
  logic so_e;
  logic [3:0] temp;
  
  piso piso_inst(.*);
  
  function void model(input logic clk, input logic rst, input logic [3:0] pi, input logic load, input logic so,  output logic [3:0] temp);    
    if(rst) begin
      so_e = 0;
      temp = 0;
    end else begin
      if(load) begin
        temp = pi;
      end else begin
        temp = temp<<1;
      end
    end
  endfunction
  
  function void compare(input logic clk, input logic rst, input logic [3:0] pi, input logic load, input logic so, input logic [3:0] temp);
    logic so_e;
    so_e = temp[3];
    
    if(so_e == so) begin
      $monitor("Time is %0t Pass : so is %0h ",$time, so);
    end else begin
      $monitor("Time is %0t Fail : so is %0h  and so_e is %0h ", $time, so, so_e);
    end   
  endfunction
  
  always@(*) begin
    #1 clk <= ~clk;
  end
    
  initial begin
    clk=0;rst=1;
    @(negedge clk);
    @(negedge clk);
    compare(clk, rst, pi,load, so, temp);
    rst=0;
      repeat(20) begin
        pi = $random();
        load = $random();
        compare(clk, rst, pi, load, so, temp);
        @(negedge clk);
      end
    $finish();
  end
  
  initial begin
    model(clk, rst, pi, load, so, temp);
    forever begin 
      @(posedge clk);
      model(clk, rst, pi, load, so, temp);
    end
  end
  initial begin
    $dumpfile("dump.vcd");
    $dumpvars;
  end
  
endmodule

Day8/Parallel_in_serial_out_RTL_design/dump.vcd
$date
	Sun Mar  5 06:29:12 2023
$end

$version
	Synopsys VCS version S-2021.09
$end

$timescale
	1ns
$end

$comment Csum: 1 5858660871d12a12 $end


$scope module piso_tb $end
$var reg 1 ! clk $end
$var reg 1 " rst $end
$var reg 4 # pi [3:0] $end
$var reg 1 $ load $end
$var reg 1 % so $end
$var reg 1 & so_e $end
$var reg 4 ' temp [3:0] $end

$scope function model $end
$var reg 1 ( clk $end
$var reg 1 ) rst $end
$var reg 4 * pi [3:0] $end
$var reg 1 + load $end
$var reg 1 , so $end
$var reg 4 - temp [3:0] $end
$upscope $end


$scope function compare $end
$var reg 1 . clk $end
$var reg 1 / rst $end
$var reg 4 0 pi [3:0] $end
$var reg 1 1 load $end
$var reg 1 2 so $end
$var reg 4 3 temp [3:0] $end
$var reg 1 4 so_e $end
$upscope $end


$scope module piso_inst $end
$var reg 1 ! clk $end
$var reg 1 " rst $end
$var reg 4 # pi [3:0] $end
$var reg 1 $ load $end
$var reg 1 % so $end
$var reg 4 5 temp [3:0] $end
$upscope $end

$upscope $end

$enddefinitions $end

#0
$dumpvars
0!
x.
x1
x/
x2
x4
x$
0(
x+
1)
x,
1"
x%
0&
bxxxx 0
bxxxx 3
bxxxx *
b0000 -
bxxxx #
bxxxx 5
b0000 '
$end
#1
1!
1(
0%
b0000 5
#2
0!
#3
1!
0,
#4
0!
0.
1/
02
b0000 3
04
0"
b0100 #
1$
0/
b0100 0
11
#5
1!
0)
b0100 *
1+
b0100 -
b0100 '
b0100 5
#6
0!
b1001 #
b1001 0
b0100 3
#7
1!
b1001 *
b1001 -
b1001 '
b1001 5
1%
#8
0!
b1101 #
b1101 0
12
b1001 3
14
#9
1!
b1101 *
1,
b1101 -
b1101 '
b1101 5
#10
0!
b0101 #
0$
b0101 0
01
b1101 3
#11
1!
b0101 *
0+
b1010 -
b1010 '
b1010 5
#12
0!
b0001 #
1$
b0001 0
11
b1010 3
#13
1!
b0001 *
1+
b0001 -
b0001 '
b0001 5
0%
#14
0!
b0110 #
b0110 0
02
b0001 3
04
#15
1!
b0110 *
0,
b0110 -
b0110 '
b0110 5
#16
0!
b1101 #
0$
b1101 0
01
b0110 3
#17
1!
b1101 *
0+
b1100 -
b1100 '
b1100 5
1%
#18
0!
b1001 #
b1001 0
12
b1100 3
14
#19
1!
b1001 *
1,
b1000 -
b1000 '
b1000 5
#20
0!
b0101 #
b0101 0
b1000 3
#21
1!
b0101 *
b0000 -
b0000 '
b0000 5
0%
#22
0!
1$
11
02
b0000 3
04
#23
1!
1+
0,
b0101 -
b0101 '
b0101 5
#24
0!
b0010 #
b0010 0
b0101 3
#25
1!
b0010 *
b0010 -
b0010 '
b0010 5
#26
0!
0$
01
b0010 3
#27
1!
0+
b0100 -
b0100 '
b0100 5
#28
0!
b1000 #
1$
b1000 0
11
b0100 3
#29
1!
b1000 *
1+
b1000 -
b1000 '
b1000 5
1%
#30
0!
b1100 #
b1100 0
12
b1000 3
14
#31
1!
b1100 *
1,
b1100 -
b1100 '
b1100 5
#32
0!
b1101 #
b1101 0
b1100 3
#33
1!
b1101 *
b1101 -
b1101 '
b1101 5
#34
0!
b0011 #
0$
b0011 0
01
b1101 3
#35
1!
b0011 *
0+
b1010 -
b1010 '
b1010 5
#36
0!
b0000 #
b0000 0
b1010 3
#37
1!
b0000 *
b0100 -
b0100 '
b0100 5
0%
#38
0!
b1010 #
1$
b1010 0
11
02
b0100 3
04
#39
1!
b1010 *
1+
0,
b1010 -
b1010 '
b1010 5
1%
#40
0!
b0110 #
b0110 0
12
b1010 3
14
#41
1!
b0110 *
1,
b0110 -
b0110 '
b0110 5
0%
#42
0!
b1101 #
b1101 0
02
b0110 3
04
#43
1!
b1101 *
0,
b1101 -
b1101 '
b1101 5
1%
