Day5/dual_port_ram_RTL_design/dual_port_ram.sv
module single_port_ram #(
  parameter DATA_WIDTH = 8,
  parameter ADDR_WIDTH = 6
)(
  input logic clk,
  input logic rst,
  input logic [DATA_WIDTH-1 : 0] data1,
  input logic [ADDR_WIDTH-1 : 0] addr1,
  input logic enable1,
  input logic [DATA_WIDTH-1 : 0] data2,
  input logic [ADDR_WIDTH-1 : 0] addr2,
  input logic enable2,
  output logic [DATA_WIDTH-1 : 0] q1,
  output logic [DATA_WIDTH-1 : 0] q2
  
);
  logic [DATA_WIDTH-1 : 0] ram[0 : 2**(ADDR_WIDTH)-1];
  
  always@(posedge clk) begin
    if(rst) begin
      q1 <= 0;
      q2 <= 0;
    end else begin
      if (enable1) begin
        ram[addr1] <= data1;
      end else begin
        q1 <= ram[addr1];
      end 
      if (enable2) begin
        ram[addr2] <= data2;
      end else begin
        q2 <= ram[addr2];
      end 
    end 
  end
endmodule

Day5/dual_port_ram_RTL_design/dual_port_ram_tb.sv
module single_port_ram_tb;
  parameter DATA_WIDTH = 8;
  parameter ADDR_WIDTH = 6;
  logic clk;
  logic rst;
  logic [DATA_WIDTH-1 : 0] data1;
  logic [ADDR_WIDTH-1 : 0] addr1;
  logic enable1;
  logic [DATA_WIDTH-1 : 0] q1;
  logic [DATA_WIDTH-1 : 0] data2;
  logic [ADDR_WIDTH-1 : 0] addr2;
  logic enable2;
  logic [DATA_WIDTH-1 : 0] q2;
  
  logic [DATA_WIDTH-1 : 0] q_e1;
  logic [DATA_WIDTH-1 : 0] q_e2;
  logic [DATA_WIDTH-1 : 0] queue1[$];
  
  
  single_port_ram single_port_ram_inst(.*);
  
  function void compare(input logic clk, input logic rst, input logic [DATA_WIDTH-1 : 0] data1, input logic [DATA_WIDTH-1 : 0] data2, input logic [ADDR_WIDTH-1 : 0] addr1, input logic [ADDR_WIDTH-1 : 0] addr2, input logic enable1, input logic enable2, input logic [DATA_WIDTH-1 : 0] q1, input logic [DATA_WIDTH-1 : 0] q2, input logic [DATA_WIDTH-1 : 0] q_e1, input logic [DATA_WIDTH-1 : 0] q_e2);
    
    logic [DATA_WIDTH-1 : 0] ram[0 : 2**(ADDR_WIDTH)-1];
    
    if(rst) begin
      q_e1 = 0;
      q_e2 = 0;
    end else begin
      if (enable1) begin
        ram[addr1] = data1;
      end else begin
        q_e1 = ram[addr1];
      end 
      if (enable2) begin
        ram[addr2] = data2;
      end else begin
        q_e2 = ram[addr2];
      end 
    end 
      
    if (enable1 == 0) begin
      if(q1 == q_e1) begin
        $display("Pass %0t: q1 is %0h", $time, q1);
      end else begin
        $display("Fail %0t : q1 is %0h and q_e1 is %0h ", $time, q1, q_e1);
      end
    end
    if (enable2 == 0) begin
      if(q2 == q_e2) begin
        $display("Pass %0t: q2 is %0h", $time, q2);
      end else begin
        $display("Fail %0t : q2 is %0h and q_e2 is %0h ", $time, q2, q_e2);
      end
    end   
  endfunction
      
  always@(*) begin
    #1 clk <= ~clk;
  end
  
  initial begin  
    clk = 0;rst = 1;
    @(posedge clk);
    @(posedge clk);
    compare(clk,rst, data1, data2, addr1, addr2, enable1, enable2, q1, q2, q_e1, q_e2);
    rst = 0;
    data1 = $random();
    addr1 = $random();
    enable1 = 1'b1;   
    queue1.push_back(addr1);
    data2 = $random();
    addr2 = $random();
    enable2 = 1'b1;   
    queue1.push_back(addr2);
    @(posedge clk);
    compare(clk,rst, data1, data2, addr1, addr2, enable1, enable2, q1, q2, q_e1, q_e2);
    repeat(20) begin
      data1 = $random();
      data2 = $random();
      queue1.shuffle();
      enable1 = $random();
      enable2 = $random();
      if(enable1 == 0) begin
        queue1.shuffle();
        addr1 = queue1[0];
      end else begin
        addr1 = $random();
      end
      if(enable2 == 0) begin
        queue1.shuffle();
        addr2 = queue1[0];
      end else begin
        addr2 = $random();
      end
         
      if(enable1) begin
        queue1.push_back(addr1); 
      end
      if(enable2) begin
        queue1.push_back(addr2); 
      end
      @(posedge clk);
      compare(clk,rst, data1, data2, addr1, addr2, enable1, enable2, q1, q2, q_e1, q_e2);
    end
    $finish();
  end
  
  initial begin
    $dumpfile("dump.vcd");
    $dumpvars;
  end
  
endmodule

Day5/dual_port_ram_RTL_design/dump.vcd
$date
	Sun Mar  5 01:42:16 2023
$end

$version
	Synopsys VCS version S-2021.09
$end

$timescale
	1ns
$end

$comment Csum: 1 61d2aa90f4cfbaa9 $end


$scope module single_port_ram_tb $end
$var reg 1 ! clk $end
$var reg 1 " rst $end
$var reg 8 # data1 [7:0] $end
$var reg 6 $ addr1 [5:0] $end
$var reg 1 % enable1 $end
$var reg 8 & q1 [7:0] $end
$var reg 8 ' data2 [7:0] $end
$var reg 6 ( addr2 [5:0] $end
$var reg 1 ) enable2 $end
$var reg 8 * q2 [7:0] $end
$var reg 8 + q_e1 [7:0] $end
$var reg 8 , q_e2 [7:0] $end

$scope begin unnamed$$_vcs_2 $end
$upscope $end


$scope begin unnamed$$_vcs_0 $end
$upscope $end


$scope begin unnamed$$_vcs_1 $end
$upscope $end


$scope module single_port_ram_inst $end
$var reg 1 ! clk $end
$var reg 1 " rst $end
$var reg 8 # data1 [7:0] $end
$var reg 6 $ addr1 [5:0] $end
$var reg 1 % enable1 $end
$var reg 8 ' data2 [7:0] $end
$var reg 6 ( addr2 [5:0] $end
$var reg 1 ) enable2 $end
$var reg 8 & q1 [7:0] $end
$var reg 8 * q2 [7:0] $end
$upscope $end

$upscope $end

$enddefinitions $end

#0
$dumpvars
0!
x%
x)
1"
bxxxxxx $
bxxxxxx (
bxxxxxxxx #
bxxxxxxxx '
bxxxxxxxx &
bxxxxxxxx *
bxxxxxxxx ,
bxxxxxxxx +
$end
#1
1!
b00000000 &
b00000000 *
#2
0!
#3
1!
0"
b00100100 #
b000001 $
1%
b00001001 '
b100011 (
1)
#4
0!
#5
1!
b00001101 #
b10001101 '
0)
b00001001 *
#6
0!
#7
1!
b01110110 '
1)
b001100 $
b111001 (
#8
0!
#9
1!
b11000110 #
b11000101 '
0%
b000001 $
b110111 (
b00001101 &
#10
0!
#11
1!
b00010010 #
b10001111 '
0)
b000001 (
b00001101 *
#12
0!
#13
1!
b11101000 #
b11000101 '
1)
b100011 $
b101101 (
b00001001 &
#14
0!
#15
1!
b01100101 #
b01100011 '
0)
b000001 $
b100011 (
b00001101 &
b00001001 *
#16
0!
#17
1!
b00100000 #
b10101010 '
1%
b010011 $
#18
0!
#19
1!
b00001101 #
b01010011 '
1)
b000010 $
b101110 (
#20
0!
#21
1!
b00011101 #
b11001111 '
0)
b001010 $
b110111 (
b11000101 *
#22
0!
#23
1!
b00111100 #
b11110010 '
0%
1)
b110111 $
b011000 (
b11000101 &
#24
0!
#25
1!
b01111000 #
b10001001 '
1%
0)
b000110 $
b110111 (
#26
0!
#27
1!
b10101110 #
b10111100 '
0%
1)
b001010 $
b110001 (
b00011101 &
#28
0!
#29
1!
b10000101 #
b01001111 '
1%
0)
b111110 $
b10111100 *
#30
0!
#31
1!
b00010101 #
b11110001 '
b001100 $
b001010 (
b00011101 *
#32
0!
#33
1!
b10011111 #
b10001111 '
0%
1)
b101110 $
b011111 (
b01010011 &
#34
0!
#35
1!
b01011100 #
b01011011 '
1%
b010000 $
b010111 (
#36
0!
#37
1!
b01010001 #
b10010110 '
0%
0)
b110001 $
b000001 (
b10111100 &
b00001101 *
#38
0!
#39
1!
b11001000 #
b01110111 '
1%
b111110 $
b000010 (
#40
0!
#41
1!
b01101101 #
b00111001 '
1)
b000101 $
b111000 (
#42
0!
#43
1!
b01011011 #
b01001001 '
0)
b011000 $
b00111001 *
