Day2/mux_rtl_design/mux.sv
module mux #(
  parameter WIDTH = 32, 
  parameter SEL_WIDTH = 1
)(
  input logic [WIDTH-1 : 0] a,
  input logic [WIDTH-1 : 0] b,
  input logic [SEL_WIDTH-1 : 0] sel,
  output logic [WIDTH-1 : 0] muxout
);
  assign muxout = sel ? a : b;
endmodule

Day2/mux_rtl_design/mux_tb.sv
module mux_tb;
  parameter WIDTH = 32; 
  parameter SEL_WIDTH = 1;
  logic [WIDTH-1 : 0] a;
  logic [WIDTH-1 : 0] b;
  logic [SEL_WIDTH-1 : 0] sel;
  logic [WIDTH-1 : 0] muxout;
  
  logic [WIDTH-1 : 0] muxout_e;
  
  mux mux_inst(.*);
  
  always@(*) begin
    case(sel)
      0: begin
           muxout_e = b;
         end
      1: begin
           muxout_e = a;
         end
      default: begin
                 muxout_e = 'hx;
               end
    endcase
  end
 
  //assign muxout_e = sel ? a : b;
  
  function void compare(input logic [WIDTH-1 : 0] a, input logic [WIDTH-1 : 0] b, input logic [SEL_WIDTH-1 : 0] sel, input logic [WIDTH-1 : 0] muxout, input logic [WIDTH-1 : 0] muxout_e);
    if(muxout == muxout_e) begin
      $display("Pass : a is %0h b is %0h sel is %0h muxout is %0h", a, b, sel, muxout);
    end else begin
      $display("Fail : a is %0h b is %0h sel is %0h muxout is %0h muxout_e is %0h", a, b, sel, muxout, muxout_e);
    end
  endfunction
  
  initial begin
    a = 0;b = 0;sel = 0;
    #1;
    compare(a, b, sel, muxout, muxout_e);
    repeat(40) begin
      a = $random();
      b = $random();
      sel = $random();
      #1;
      compare(a, b, sel, muxout, muxout_e);
    end
  end
    
  initial begin
    $dumpfile("dump.vcd");
    $dumpvars;
  end
endmodule

Day2/mux_rtl_design/dump.vcd
$date
	Sat Feb 25 10:29:15 2023
$end

$version
	Synopsys VCS version S-2021.09
$end

$timescale
	1ns
$end

$comment Csum: 1 670698b3e097791e $end


$scope module mux_tb $end
$var reg 32 ! a [31:0] $end
$var reg 32 " b [31:0] $end
$var reg 1 # sel [0:0] $end
$var reg 32 $ muxout [31:0] $end
$var reg 32 % muxout_e [31:0] $end

$scope function compare $end
$var reg 32 & a [31:0] $end
$var reg 32 ' b [31:0] $end
$var reg 1 ( sel [0:0] $end
$var reg 32 ) muxout [31:0] $end
$var reg 32 * muxout_e [31:0] $end
$upscope $end


$scope module mux_inst $end
$var reg 32 ! a [31:0] $end
$var reg 32 " b [31:0] $end
$var reg 1 # sel [0:0] $end
$var reg 32 $ muxout [31:0] $end
$upscope $end

$upscope $end

$enddefinitions $end

#0
$dumpvars
x(
0#
b00000000000000000000000000000000 !
b00000000000000000000000000000000 "
bxxxxxxxxxxxxxxxxxxxxxxxxxxxxxxxx &
bxxxxxxxxxxxxxxxxxxxxxxxxxxxxxxxx '
bxxxxxxxxxxxxxxxxxxxxxxxxxxxxxxxx )
bxxxxxxxxxxxxxxxxxxxxxxxxxxxxxxxx *
b00000000000000000000000000000000 $
b00000000000000000000000000000000 %
$end
#1
b00000000000000000000000000000000 &
b00000000000000000000000000000000 '
0(
b00000000000000000000000000000000 )
b00000000000000000000000000000000 *
b00010010000101010011010100100100 !
b11000000100010010101111010000001 "
1#
b00010010000101010011010100100100 %
b00010010000101010011010100100100 $
#2
b00010010000101010011010100100100 &
b11000000100010010101111010000001 '
1(
b00010010000101010011010100100100 )
b00010010000101010011010100100100 *
b10110001111100000101011001100011 !
b00000110101110010111101100001101 "
b10110001111100000101011001100011 %
b10110001111100000101011001100011 $
#3
b10110001111100000101011001100011 &
b00000110101110010111101100001101 '
b10110001111100000101011001100011 )
b10110001111100000101011001100011 *
b10110010110000101000010001100101 !
b10001001001101110101001000010010 "
b10110010110000101000010001100101 %
b10110010110000101000010001100101 $
#4
b10110010110000101000010001100101 &
b10001001001101110101001000010010 '
b10110010110000101000010001100101 )
b10110010110000101000010001100101 *
b00000110110101111100110100001101 !
b00111011001000111111000101110110 "
b00000110110101111100110100001101 %
b00000110110101111100110100001101 $
#5
b00000110110101111100110100001101 &
b00111011001000111111000101110110 '
b00000110110101111100110100001101 )
b00000110110101111100110100001101 *
b01110110110101000101011111101101 !
b01000110001011011111011110001100 "
b01110110110101000101011111101101 %
b01110110110101000101011111101101 $
#6
b01110110110101000101011111101101 &
b01000110001011011111011110001100 '
b01110110110101000101011111101101 )
b01110110110101000101011111101101 *
b11100011001101110010010011000110 !
b11100010111101111000010011000101 "
0#
b11100010111101111000010011000101 %
b11100010111101111000010011000101 $
#7
b11100011001101110010010011000110 &
b11100010111101111000010011000101 '
0(
b11100010111101111000010011000101 )
b11100010111101111000010011000101 *
b01110010101011111111011111100101 !
b10111011110100100111001001110111 "
b10111011110100100111001001110111 %
b10111011110100100111001001110111 $
#8
b01110010101011111111011111100101 &
b10111011110100100111001001110111 '
b10111011110100100111001001110111 )
b10111011110100100111001001110111 *
b01000111111011001101101110001111 !
b01111001001100000110100111110010 "
b01111001001100000110100111110010 %
b01111001001100000110100111110010 $
#9
b01000111111011001101101110001111 &
b01111001001100000110100111110010 '
b01111001001100000110100111110010 )
b01111001001100000110100111110010 *
b11110100000000000111101011101000 !
b11100010110010100100111011000101 "
b11100010110010100100111011000101 %
b11100010110010100100111011000101 $
#10
b11110100000000000111101011101000 &
b11100010110010100100111011000101 '
b11100010110010100100111011000101 )
b11100010110010100100111011000101 *
b11011110100011100010100010111101 !
b10010110101010110101100000101101 "
1#
b11011110100011100010100010111101 %
b11011110100011100010100010111101 $
#11
b11011110100011100010100010111101 &
b10010110101010110101100000101101 '
1(
b11011110100011100010100010111101 )
b11011110100011100010100010111101 *
b10110001111011110110001001100011 !
b00000101011100111000011100001010 "
0#
b00000101011100111000011100001010 %
b00000101011100111000011100001010 $
#12
b10110001111011110110001001100011 &
b00000101011100111000011100001010 '
0(
b00000101011100111000011100001010 )
b00000101011100111000011100001010 *
b00010000011001000010000100100000 !
b01010101011110000100010110101010 "
1#
b00010000011001000010000100100000 %
b00010000011001000010000100100000 $
#13
b00010000011001000010000100100000 &
b01010101011110000100010110101010 '
1(
b00010000011001000010000100100000 )
b00010000011001000010000100100000 *
b11001011001000000011111010010110 !
b10001001100000111011100000010011 "
b11001011001000000011111010010110 %
b11001011001000000011111010010110 $
#14
b11001011001000000011111010010110 &
b10001001100000111011100000010011 '
b11001011001000000011111010010110 )
b11001011001000000011111010010110 *
b10101001101001111101011001010011 !
b00110101100111111101110101101011 "
b10101001101001111101011001010011 %
b10101001101001111101011001010011 $
#15
b10101001101001111101011001010011 &
b00110101100111111101110101101011 '
b10101001101001111101011001010011 )
b10101001101001111101011001010011 *
b10000001000101110100101000000010 !
b11010111010101100011111010101110 "
b10000001000101110100101000000010 %
b10000001000101110100101000000010 $
#16
b10000001000101110100101000000010 &
b11010111010101100011111010101110 '
b10000001000101110100101000000010 )
b10000001000101110100101000000010 *
b11100111110001010111001011001111 !
b00010001100001000100100100100011 "
0#
b00010001100001000100100100100011 %
b00010001100001000100100100100011 $
#17
b11100111110001010111001011001111 &
b00010001100001000100100100100011 '
0(
b00010001100001000100100100100011 )
b00010001100001000100100100100011 *
b11100101011100110000101011001010 !
b10011110001100010100110000111100 "
b10011110001100010100110000111100 %
b10011110001100010100110000111100 $
#18
b11100101011100110000101011001010 &
b10011110001100010100110000111100 '
b10011110001100010100110000111100 )
b10011110001100010100110000111100 *
b01000101001011100110000110001010 !
b00100000110001001011001101000001 "
b00100000110001001011001101000001 %
b00100000110001001011001101000001 $
#19
b01000101001011100110000110001010 &
b00100000110001001011001101000001 '
b00100000110001001011001101000001 )
b00100000110001001011001101000001 *
b00111100001000001111001101111000 !
b11000100100010100001001010001001 "
1#
b00111100001000001111001101111000 %
b00111100001000001111001101111000 $
#20
b00111100001000001111001101111000 &
b11000100100010100001001010001001 '
1(
b00111100001000001111001101111000 )
b00111100001000001111001101111000 *
b01011011000000100110010110110110 !
b01100011010010111111100111000110 "
0#
b01100011010010111111100111000110 %
b01100011010010111111100111000110 $
#21
b01011011000000100110010110110110 &
b01100011010010111111100111000110 '
0(
b01100011010010111111100111000110 )
b01100011010010111111100111000110 *
b11011110011101010000001010111100 !
b00010101000011111101110100101010 "
1#
b11011110011101010000001010111100 %
b11011110011101010000001010111100 $
#22
b11011110011101010000001010111100 &
b00010101000011111101110100101010 '
1(
b11011110011101010000001010111100 )
b11011110011101010000001010111100 *
b10111000100101111011111001110001 !
b01000010111100100100000110000101 "
b10111000100101111011111001110001 %
b10111000100101111011111001110001 $
#23
b10111000100101111011111001110001 &
b01000010111100100100000110000101 '
b10111000100101111011111001110001 )
b10111000100101111011111001110001 *
b10011101110011000110000000111011 !
b00011101000001100011001100111010 "
0#
b00011101000001100011001100111010 %
b00011101000001100011001100111010 $
#24
b10011101110011000110000000111011 &
b00011101000001100011001100111010 '
0(
b00011101000001100011001100111010 )
b00011101000001100011001100111010 *
b00001010101010100100101100010101 !
b01111000110110011001101111110001 "
1#
b00001010101010100100101100010101 %
b00001010101010100100101100010101 $
#25
b00001010101010100100101100010101 &
b01111000110110011001101111110001 '
1(
b00001010101010100100101100010101 )
b00001010101010100100101100010101 *
b00110001001000110000011101100010 !
b00100110001101011111101101001100 "
b00110001001000110000011101100010 %
b00110001001000110000011101100010 $
#26
b00110001001000110000011101100010 &
b00100110001101011111101101001100 '
b00110001001000110000011101100010 )
b00110001001000110000011101100010 *
b01000111101110011010000110001111 !
b01111100011011011010100111111000 "
b01000111101110011010000110001111 %
b01000111101110011010000110001111 $
#27
b01000111101110011010000110001111 &
b01111100011011011010100111111000 '
b01000111101110011010000110001111 )
b01000111101110011010000110001111 *
b11001111110001000101011010011111 !
b10101110011111011001010001011100 "
b11001111110001000101011010011111 %
b11001111110001000101011010011111 $
#28
b11001111110001000101011010011111 &
b10101110011111011001010001011100 '
b11001111110001000101011010011111 )
b11001111110001000101011010011111 *
b01000100110111100011011110001001 !
b10100100101011100011001001001001 "
0#
b10100100101011100011001001001001 %
b10100100101011100011001001001001 $
#29
b01000100110111100011011110001001 &
b10100100101011100011001001001001 '
0(
b10100100101011100011001001001001 )
b10100100101011100011001001001001 *
b11101011111111101100000011010111 !
b10101000110001111111110001010001 "
b10101000110001111111110001010001 %
b10101000110001111111110001010001 $
#30
b11101011111111101100000011010111 &
b10101000110001111111110001010001 '
b10101000110001111111110001010001 )
b10101000110001111111110001010001 *
b00000110000111010111111100001100 !
b11100001001011001100111011000010 "
b11100001001011001100111011000010 %
b11100001001011001100111011000010 $
#31
b00000110000111010111111100001100 &
b11100001001011001100111011000010 '
b11100001001011001100111011000010 )
b11100001001011001100111011000010 *
b10111011100000100101101001110111 !
b00011110111100101110110100111101 "
b00011110111100101110110100111101 %
b00011110111100101110110100111101 $
#32
b10111011100000100101101001110111 &
b00011110111100101110110100111101 '
b00011110111100101110110100111101 )
b00011110111100101110110100111101 *
b10111111000001010000000001111110 !
b00110110111001011000000101101101 "
1#
b10111111000001010000000001111110 %
b10111111000001010000000001111110 $
#33
b10111111000001010000000001111110 &
b00110110111001011000000101101101 '
1(
b10111111000001010000000001111110 )
b10111111000001010000000001111110 *
b00001111110100101000111100011111 !
b11101001111010111111011011010011 "
b00001111110100101000111100011111 %
b00001111110100101000111100011111 $
#34
b00001111110100101000111100011111 &
b11101001111010111111011011010011 '
b00001111110100101000111100011111 )
b00001111110100101000111100011111 *
b10111100000101001000100001111000 !
b00101101110110100101100101011011 "
b10111100000101001000100001111000 %
b10111100000101001000100001111000 $
#35
b10111100000101001000100001111000 &
b00101101110110100101100101011011 '
b10111100000101001000100001111000 )
b10111100000101001000100001111000 *
b10011111111100101010111000111111 !
b00010101000011001010111100101010 "
0#
b00010101000011001010111100101010 %
b00010101000011001010111100101010 $
#36
b10011111111100101010111000111111 &
b00010101000011001010111100101010 '
0(
b00010101000011001010111100101010 )
b00010101000011001010111100101010 *
b11000011001111110011100010000110 !
b11000111000110100000110010001110 "
b11000111000110100000110010001110 %
b11000111000110100000110010001110 $
#37
b11000011001111110011100010000110 &
b11000111000110100000110010001110 '
b11000111000110100000110010001110 )
b11000111000110100000110010001110 *
b01111101001101011001100111111010 !
b10010011011111011011110000100110 "
1#
b01111101001101011001100111111010 %
b01111101001101011001100111111010 $
#38
b01111101001101011001100111111010 &
b10010011011111011011110000100110 '
1(
b01111101001101011001100111111010 )
b01111101001101011001100111111010 *
b11010001100010111011010010100011 !
b10010111100110011010100000101111 "
b11010001100010111011010010100011 %
b11010001100010111011010010100011 $
#39
b11010001100010111011010010100011 &
b10010111100110011010100000101111 '
b11010001100010111011010010100011 )
b11010001100010111011010010100011 *
b10101111110110000101011001011111 !
b00100010001010010000110101000100 "
b10101111110110000101011001011111 %
b10101111110110000101011001011111 $
#40
b10101111110110000101011001011111 &
b00100010001010010000110101000100 '
b10101111110110000101011001011111 )
b10101111110110000101011001011111 *
b11100101100110110011011011001011 !
b11110011000010010001101011100110 "
0#
b11110011000010010001101011100110 %
b11110011000010010001101011100110 $
#41
b11100101100110110011011011001011 &
b11110011000010010001101011100110 '
0(
b11110011000010010001101011100110 )
b11110011000010010001101011100110 *
