Day_14/Fibonacci series/fibonacci.sv
module fibonacci (
  input logic clk,
  input logic rst,
  input int size,
  output int out
);
  int ptr;
  int q[$];
  
  always@(posedge clk) begin
    if(rst) begin
      out <= 0;
      ptr <= 0;
    end else begin
      
      if(ptr == 0) begin
        out <= 0;
        ptr <= ptr + 1;
        q.push_back(0);
      end else if(ptr == 1) begin
        out <= 1;
        ptr <= ptr + 1;
        q.push_back(1);
      end else begin
        out <= q[ptr-1] + q[ptr-2];        
        q.push_back(q[ptr-1]+q[ptr-2]);
        ptr <= ptr + 1;
      end     
    end
  end
  
endmodule

Day_14/Fibonacci series/fibonacci_tb.sv
module fibonacci_tb();
  logic clk;
  logic rst;
  int out;
  int size;
  
  
  fibonacci fibonacci_inst(.*);
  
  always@(*) begin
    #1 clk <= ~clk;
  end
  
  initial begin
    clk=0; rst=1;
    @(posedge clk);
    @(posedge clk);
    $display("out is %0h ",out);
    rst=0;
    size=10;
    repeat(size) begin
      @(posedge clk);
      $display("out is %0h ",out); 
    end
    $finish();  
  end
  
  initial begin
    $dumpfile("dump.vcd");
    $dumpvars(0);
  end
  
  
endmodule

Day_14/Fibonacci series/dump.vcd
$date
	Sun Apr 30 03:20:07 2023
$end

$version
	Synopsys VCS version S-2021.09
$end

$timescale
	1ns
$end

$comment Csum: 1 69b9ae42617712a2 $end


$scope module fibonacci_tb $end
$var reg 1 ! clk $end
$var reg 1 " rst $end
$var reg 32 # out [31:0] $end
$var reg 32 $ size [31:0] $end

$scope module fibonacci_inst $end
$var reg 1 ! clk $end
$var reg 1 " rst $end
$var reg 32 $ size [31:0] $end
$var reg 32 # out [31:0] $end
$var reg 32 % ptr [31:0] $end

$scope begin unnamed$$_vcs_0 $end
$upscope $end

$upscope $end

$upscope $end

$enddefinitions $end

#0
$dumpvars
0!
1"
b00000000000000000000000000000000 #
b00000000000000000000000000000000 %
b00000000000000000000000000000000 $
$end
#1
1!
#2
0!
#3
1!
0"
b00000000000000000000000000001010 $
b00000000000000000000000000000001 %
#4
0!
#5
1!
b00000000000000000000000000000001 #
b00000000000000000000000000000010 %
#6
0!
#7
1!
b00000000000000000000000000000011 %
#8
0!
#9
1!
b00000000000000000000000000000010 #
b00000000000000000000000000000100 %
#10
0!
#11
1!
b00000000000000000000000000000011 #
b00000000000000000000000000000101 %
#12
0!
#13
1!
b00000000000000000000000000000101 #
b00000000000000000000000000000110 %
#14
0!
#15
1!
b00000000000000000000000000001000 #
b00000000000000000000000000000111 %
#16
0!
#17
1!
b00000000000000000000000000001101 #
b00000000000000000000000000001000 %
#18
0!
#19
1!
b00000000000000000000000000010101 #
b00000000000000000000000000001001 %
#20
0!
#21
1!
b00000000000000000000000000100010 #
b00000000000000000000000000001010 %
